Workbook

Sheet Inputs
A1: Modelo de Valuation - Fabrica Reis / marcas Lelooks e Piratas for men
A3: Premissas operacionais editaveis
A4: Receita base 2025 | B4: 18000000 | C4: Receita liquida anual normalizada da fabrica | D4: R$
A5: Participacao Lelooks | B5: 0.58 | C5: Mix de receita feminina | D5: %
A6: Participacao Piratas for men | B6: =1-B5 | C6: Mix de receita masculina | D6: %
A7: Crescimento receita ano 1 | B7: 0.12 | C7: Expansao de vendas | D7: %
A8: Crescimento receita ano 2 | B8: 0.1 | C8: Expansao de vendas | D8: %
A9: Crescimento receita ano 3 | B9: 0.08 | C9: Expansao de vendas | D9: %
A10: Crescimento receita ano 4 | B10: 0.07 | C10: Expansao de vendas | D10: %
A11: Crescimento receita ano 5 | B11: 0.06 | C11: Expansao de vendas | D11: %
A12: Margem bruta | B12: 0.48 | C12: Receita menos CPV | D12: %
A13: Despesas comerciais/administrativas | B13: 0.28 | C13: SG&A sobre receita | D13: %
A14: Ajustes de EBITDA | B14: 0 | C14: Ajustes recorrentes: pro-labore, alugueis, one-offs | D14: R$
A15: Depreciacao / receita | B15: 0.03 | C15: Depreciacao e amortizacao | D15: %
A16: Capex / receita | B16: 0.04 | C16: Reposicao e expansao de maquinas | D16: %
A17: Capital de giro / incremento receita | B17: 0.12 | C17: Necessidade incremental | D17: %
A18: Aliquota IR/CSLL efetiva | B18: 0.24 | C18: Taxa efetiva estimada | D18: %
A21: Taxa de desconto: build-up de risco setorial
A22: Taxa livre de risco / CDI longo prazo | B22: 0.105 | C22: Base Brasil nominal | D22: %
A23: Premio de risco de mercado | B23: 0.065 | C23: Risco de equity | D23: %
A24: Beta desalavancado moda/varejo | B24: 0.9 | C24: Sensibilidade setorial | D24: x
A25: Premio tamanho/empresa fechada | B25: 0.035 | C25: Pequena empresa e liquidez | D25: %
A26: Premio concentracao de clientes/canais | B26: 0.02 | C26: Dependencia comercial | D26: %
A27: Premio moda/estoque/sazonalidade | B27: 0.02 | C27: Colecoes, ruptura e markdowns | D27: %
A28: Custo de capital proprio | B28: =B22+B23*B24+B25+B26+B27 | C28: CAPM ajustado | D28: %
A29: Custo da divida antes IR | B29: 0.145 | C29: Custo bancario estimado | D29: %
A30: Peso equity | B30: 0.75 | C30: Estrutura alvo | D30: %
A31: Peso divida | B31: =1-B30 | C31: Estrutura alvo | D31: %
A32: WACC nominal | B32: =B30*B28+B31*B29*(1-B18) | C32: Taxa de desconto FCD | D32: %
A33: Crescimento perpetuo | B33: 0.045 | C33: Terminal nominal conservador | D33: %
A36: Pesos do valor final
A37: Peso FCD | B37: 0.55
A38: Peso multiplos | B38: 0.25
A39: Peso patrimonial | B39: 0.2
A40: Total | B40: =SUM(B37:B39)

Sheet FCD
A1: Fluxo de Caixa Descontado | B1: 2025 base | C1: Ano 1 | D1: Ano 2 | E1: Ano 3 | F1: Ano 4 | G1: Ano 5
A2: Receita liquida | B2: =Inputs!B4 | C2: =B2*(1+Inputs!B7) | D2: =C2*(1+Inputs!B8) | E2: =D2*(1+Inputs!B9) | F2: =E2*(1+Inputs!B10) | G2: =F2*(1+Inputs!B11)
A3: Lelooks | B3: =B2*Inputs!B5 | C3: =C2*Inputs!B5 | D3: =D2*Inputs!B5 | E3: =E2*Inputs!B5 | F3: =F2*Inputs!B5 | G3: =G2*Inputs!B5
A4: Piratas for men | B4: =B2*Inputs!B6 | C4: =C2*Inputs!B6 | D4: =D2*Inputs!B6 | E4: =E2*Inputs!B6 | F4: =F2*Inputs!B6 | G4: =G2*Inputs!B6
A5: CPV | B5: =-B2*(1-Inputs!B12) | C5: =-C2*(1-Inputs!B12) | D5: =-D2*(1-Inputs!B12) | E5: =-E2*(1-Inputs!B12) | F5: =-F2*(1-Inputs!B12) | G5: =-G2*(1-Inputs!B12)
A6: Lucro bruto | B6: =B2+B5 | C6: =C2+C5 | D6: =D2+D5 | E6: =E2+E5 | F6: =F2+F5 | G6: =G2+G5
A7: Despesas comerciais/adm. | B7: =-B2*Inputs!B13 | C7: =-C2*Inputs!B13 | D7: =-D2*Inputs!B13 | E7: =-E2*Inputs!B13 | F7: =-F2*Inputs!B13 | G7: =-G2*Inputs!B13
A8: EBITDA ajustado | B8: =B6+B7+Inputs!B14 | C8: =C6+C7+Inputs!B14 | D8: =D6+D7+Inputs!B14 | E8: =E6+E7+Inputs!B14 | F8: =F6+F7+Inputs!B14 | G8: =G6+G7+Inputs!B14
A9: Margem EBITDA | B9: =B8/B2 | C9: =C8/C2 | D9: =D8/D2 | E9: =E8/E2 | F9: =F8/F2 | G9: =G8/G2
A10: Depreciacao | B10: =-B2*Inputs!B15 | C10: =-C2*Inputs!B15 | D10: =-D2*Inputs!B15 | E10: =-E2*Inputs!B15 | F10: =-F2*Inputs!B15 | G10: =-G2*Inputs!B15
A11: EBIT | B11: =B8+B10 | C11: =C8+C10 | D11: =D8+D10 | E11: =E8+E10 | F11: =F8+F10 | G11: =G8+G10
A12: Impostos | B12: =-MAX(0,B11)*Inputs!B18 | C12: =-MAX(0,C11)*Inputs!B18 | D12: =-MAX(0,D11)*Inputs!B18 | E12: =-MAX(0,E11)*Inputs!B18 | F12: =-MAX(0,F11)*Inputs!B18 | G12: =-MAX(0,G11)*Inputs!B18
A13: NOPAT | B13: =B11+B12 | C13: =C11+C12 | D13: =D11+D12 | E13: =E11+E12 | F13: =F11+F12 | G13: =G11+G12
A14: + Depreciacao | B14: =-B10 | C14: =-C10 | D14: =-D10 | E14: =-E10 | F14: =-F10 | G14: =-G10
A15: - Capex | B15: =-B2*Inputs!B16 | C15: =-C2*Inputs!B16 | D15: =-D2*Inputs!B16 | E15: =-E2*Inputs!B16 | F15: =-F2*Inputs!B16 | G15: =-G2*Inputs!B16
A16: - Capital de giro incremental | B16: 0 | C16: =-(C2-B2)*Inputs!B17 | D16: =-(D2-C2)*Inputs!B17 | E16: =-(E2-D2)*Inputs!B17 | F16: =-(F2-E2)*Inputs!B17 | G16: =-(G2-F2)*Inputs!B17
A17: Fluxo de caixa livre | B17: =SUM(B13:B16) | C17: =SUM(C13:C16) | D17: =SUM(D13:D16) | E17: =SUM(E13:E16) | F17: =SUM(F13:F16) | G17: =SUM(G13:G16)
A18: Fator desconto | C18: =1/(1+Inputs!B32)^1 | D18: =1/(1+Inputs!B32)^2 | E18: =1/(1+Inputs!B32)^3 | F18: =1/(1+Inputs!B32)^4 | G18: =1/(1+Inputs!B32)^5
A19: VP FCL | C19: =C17*C18 | D19: =D17*D18 | E19: =E17*E18 | F19: =F17*F18 | G19: =G17*G18
A20: Valor terminal | G20: =G17*(1+Inputs!B33)/(Inputs!B32-Inputs!B33)
A21: VP valor terminal | G21: =G20*G18
A22: Enterprise value FCD | G22: =SUM(C19:G19)+G21

Sheet Multiplos
A1: Pares brasileiros de moda/textil | B1: Ticker | C1: Receita LTM / anual | D1: EBITDA LTM / anual | E1: EV/Receita | F1: EV/EBITDA | G1: P/L | H1: Observacao
A2: Lojas Renner | B2: LREN3 | C2: 13838200000 | D2: 3200000000 | E2: 1.1 | F2: 5.3 | G2: 13 | H2: Varejo moda omnichannel
A3: Riachuelo / Guararapes | B3: RIAA3 | C3: 10500000000 | D3: 1800000000 | E3: 0.7 | F3: 4.2 | G3: 9.5 | H3: Varejo moda + financeiro
A4: C&A Brasil | B4: CEAB3 | C4: 7980000000 | D4: 1240000000 | E4: 0.6 | F4: 4 | G4: 8.5 | H4: Varejo moda
A5: Azzas 2154 | B5: AZZA3 | C5: 11800000000 | D5: 1940000000 | E5: 1 | F5: 7 | G5: 14 | H5: Grupo de marcas
A6: Vulcabras | B6: VULC3 | C6: 4200000000 | D6: 763100000 | E6: 1.3 | F6: 6.2 | G6: 10.5 | H6: Calcados e vestuario esportivo
A7: Mediana | C7: =MEDIAN(C2:C6) | D7: =MEDIAN(D2:D6) | E7: =MEDIAN(E2:E6) | F7: =MEDIAN(F2:F6) | G7: =MEDIAN(G2:G6)
A8: Desconto empresa fechada/tamanho | E8: 0.3 | F8: 0.3 | G8: 0.3 | H8: Ajustavel
A9: Multiplo aplicado | E9: =E7*(1-E8) | F9: =F7*(1-F8) | G9: =G7*(1-G8)
A10: Receita Reis Ano 1 | C10: =FCD!C2
A11: EBITDA Reis Ano 1 | D11: =FCD!C8
A12: Lucro liquido proxy | D12: =FCD!C13 | H12: NOPAT como proxy
A13: Valor por EV/Receita | E13: =C10*E9
A14: Valor por EV/EBITDA | F14: =D11*F9
A15: Valor por P/L | G15: =D12*G9
A16: Enterprise value por multiplos | G16: =AVERAGE(E13,F14,G15)

Sheet Patrimonial
A1: Valor Patrimonial Ajustado | B1: Valor contabil | C1: Ajuste a mercado | D1: Valor ajustado | E1: Observacao
A2: Maquinas de corte/costura/acabamento | B2: 2200000 | C2: 0.1 | D2: =B2*(1+C2) | E2: Atualizar por laudo/valor de reposicao
A3: Instalacoes e benfeitorias | B3: 900000 | C3: 0 | D3: =B3*(1+C3) | E3: Galpao, layout fabril, eletrica
A4: Estoque materia-prima e acabado | B4: 3400000 | C4: -0.08 | D4: =B4*(1+C4) | E4: Aplicar markdown/obsolescencia
A5: Contas a receber | B5: 1900000 | C5: -0.03 | D5: =B5*(1+C5) | E5: Risco de inadimplencia
A6: Caixa e equivalentes | B6: 450000 | C6: 0 | D6: =B6*(1+C6)
A7: Outros ativos | B7: 250000 | C7: 0 | D7: =B7*(1+C7)
A8: Dividas bancarias | B8: -2800000 | C8: 0 | D8: =B8*(1+C8) | E8: Valor liquido negativo
A9: Fornecedores/impostos/contingencias | B9: -1200000 | C9: 0 | D9: =B9*(1+C9) | E9: Valor liquido negativo
A10: Patrimonio liquido ajustado | D10: =SUM(D2:D9)
A12: Intangiveis de marca | B12: Receita atribuida | C12: Royalty rate | D12: Valor da marca | E12: Observacao
A13: Marca Lelooks | B13: =FCD!C2*Inputs!B5 | C13: 0.025 | D13: =B13*C13*(1-Inputs!B18)/(Inputs!B32-Inputs!B33) | E13: Metodo relief-from-royalty
A14: Marca Piratas for men | B14: =FCD!C2*Inputs!B6 | C14: 0.02 | D14: =B14*C14*(1-Inputs!B18)/(Inputs!B32-Inputs!B33) | E14: Metodo relief-from-royalty
A15: Valor patrimonial + intangiveis | D15: =D10+SUM(D13:D14)

Sheet Sensibilidade
A1: Sensibilidade FCD - EV por WACC e crescimento perpetuo
A2: WACC \ g | B2: 0.025 | C2: 0.035 | D2: 0.045 | E2: 0.055 | F2: 0.065
A3: 0.145 | B3: =SUM(FCD!C19:G19)+FCD!G17*(1+B2)/(A3-B2)*FCD!G18 | C3: =SUM(FCD!C19:G19)+FCD!G17*(1+C2)/(A3-C2)*FCD!G18 | D3: =SUM(FCD!C19:G19)+FCD!G17*(1+D2)/(A3-D2)*FCD!G18 | E3: =SUM(FCD!C19:G19)+FCD!G17*(1+E2)/(A3-E2)*FCD!G18 | F3: =SUM(FCD!C19:G19)+FCD!G17*(1+F2)/(A3-F2)*FCD!G18
A4: 0.16 | B4: =SUM(FCD!C19:G19)+FCD!G17*(1+B2)/(A4-B2)*FCD!G18 | C4: =SUM(FCD!C19:G19)+FCD!G17*(1+C2)/(A4-C2)*FCD!G18 | D4: =SUM(FCD!C19:G19)+FCD!G17*(1+D2)/(A4-D2)*FCD!G18 | E4: =SUM(FCD!C19:G19)+FCD!G17*(1+E2)/(A4-E2)*FCD!G18 | F4: =SUM(FCD!C19:G19)+FCD!G17*(1+F2)/(A4-F2)*FCD!G18
A5: 0.175 | B5: =SUM(FCD!C19:G19)+FCD!G17*(1+B2)/(A5-B2)*FCD!G18 | C5: =SUM(FCD!C19:G19)+FCD!G17*(1+C2)/(A5-C2)*FCD!G18 | D5: =SUM(FCD!C19:G19)+FCD!G17*(1+D2)/(A5-D2)*FCD!G18 | E5: =SUM(FCD!C19:G19)+FCD!G17*(1+E2)/(A5-E2)*FCD!G18 | F5: =SUM(FCD!C19:G19)+FCD!G17*(1+F2)/(A5-F2)*FCD!G18
A6: 0.19 | B6: =SUM(FCD!C19:G19)+FCD!G17*(1+B2)/(A6-B2)*FCD!G18 | C6: =SUM(FCD!C19:G19)+FCD!G17*(1+C2)/(A6-C2)*FCD!G18 | D6: =SUM(FCD!C19:G19)+FCD!G17*(1+D2)/(A6-D2)*FCD!G18 | E6: =SUM(FCD!C19:G19)+FCD!G17*(1+E2)/(A6-E2)*FCD!G18 | F6: =SUM(FCD!C19:G19)+FCD!G17*(1+F2)/(A6-F2)*FCD!G18
A7: 0.205 | B7: =SUM(FCD!C19:G19)+FCD!G17*(1+B2)/(A7-B2)*FCD!G18 | C7: =SUM(FCD!C19:G19)+FCD!G17*(1+C2)/(A7-C2)*FCD!G18 | D7: =SUM(FCD!C19:G19)+FCD!G17*(1+D2)/(A7-D2)*FCD!G18 | E7: =SUM(FCD!C19:G19)+FCD!G17*(1+E2)/(A7-E2)*FCD!G18 | F7: =SUM(FCD!C19:G19)+FCD!G17*(1+F2)/(A7-F2)*FCD!G18
A9: Sensibilidade multiplos - EV por margem EBITDA e EV/EBITDA
A10: 0.12 | B10: =FCD!C2*A10*B9 | C10: =FCD!C2*A10*C9 | D10: =FCD!C2*A10*D9 | E10: =FCD!C2*A10*E9 | F10: =FCD!C2*A10*F9
A11: 0.16 | B11: =FCD!C2*A11*B9 | C11: =FCD!C2*A11*C9 | D11: =FCD!C2*A11*D9 | E11: =FCD!C2*A11*E9 | F11: =FCD!C2*A11*F9
A12: 0.2 | B12: =FCD!C2*A12*B9 | C12: =FCD!C2*A12*C9 | D12: =FCD!C2*A12*D9 | E12: =FCD!C2*A12*E9 | F12: =FCD!C2*A12*F9
A13: 0.24 | B13: =FCD!C2*A13*B9 | C13: =FCD!C2*A13*C9 | D13: =FCD!C2*A13*D9 | E13: =FCD!C2*A13*E9 | F13: =FCD!C2*A13*F9
A14: 0.28 | B14: =FCD!C2*A14*B9 | C14: =FCD!C2*A14*C9 | D14: =FCD!C2*A14*D9 | E14: =FCD!C2*A14*E9 | F14: =FCD!C2*A14*F9

Sheet Resumo
A1: Resumo do Valuation - Fabrica Reis
A2: Enterprise value FCD | B2: =FCD!G22 | C2: Peso | D2: =Inputs!B37
A3: Enterprise value por multiplos | B3: =Multiplos!G16 | C3: Peso | D3: =Inputs!B38
A4: Valor patrimonial + intangiveis | B4: =Patrimonial!D15 | C4: Peso | D4: =Inputs!B39
A5: Valor final estimado ponderado | B5: =SUMPRODUCT(B2:B4,D2:D4)/SUM(D2:D4)
A6: Faixa baixa (-15%) | B6: =B5*0.85
A7: Faixa alta (+15%) | B7: =B5*1.15
A8: Margem EBITDA ano 1 | B8: =FCD!C9
A9: WACC | B9: =Inputs!B32
A10: Crescimento perpetuo | B10: =Inputs!B33

Sheet Fontes
A1: Data de elaboracao | B1: 16/04/2026
A2: Observacao | B2: Multiples sao inputs editaveis e devem ser atualizados com cotacoes/EV do dia antes de uma decisao vinculante.
A3: Fonte | B3: Link | C3: Uso no modelo
A4: InfoMoney - Riachuelo 4T25 | B4: https://www.infomoney.com.br/mercados/riachuelo-riaa3-resultados-quarto-trimestre-2025/ | C4: Receita/EBITDA de referencia setorial
A5: FashionUnited - Riachuelo 2025 | B5: https://fashionunited.com/news/business/riachuelo-parent-company-guararapes-ends-2025-with-over-100-percent-growth/2026022370741 | C5: Resultados anuais 2025 e valor de mercado citado
A6: Visno Invest - Lojas Renner 2025 | B6: https://visnoinvest.com.br/news/11946/lojas-renner-lren3-registra-lucro-de-1-5-bi-em-2025 | C6: Receita e EBITDA anual de par
A7: Revista Fator Brasil - C&A 2025 | B7: https://www.revistafatorbrasil.com.br/2026/02/26/ca-apresenta-lucro-liquido-de-r-5871-milhoes-em-2025-com-alta-de-297/ | C7: Receita e indicadores de par
A8: ADVFN - Azzas 2154 4T25 | B8: https://br.advfn.com/jornal/2026/03/azzas-2154-tem-lucro-liquido-de-r-168-milhoes-no-4t25-resultado-anual-sobe-30-5-em-2025 | C8: EBITDA e lucro de par
A9: BP Money - Vulcabras 4T25 | B9: https://bpmoney.com.br/mercado/vulcabras-vulc3-lucra-r-1588-milhoes-no-4t25-queda-de-61/ | C9: EBITDA e receita de par
